enumerific/__init__.py
enumerific/exceptions.py
enumerific/extensible.py
enumerific/logging.py
enumerific/standard.py
enumerific/version.txt
enumerific-1.0.9.dist-info/licenses/LICENSE.md
enumerific-1.0.9.dist-info/METADATA
enumerific-1.0.9.dist-info/WHEEL
enumerific-1.0.9.dist-info/top_level.txt
enumerific-1.0.9.dist-info/zip-safe
enumerific-1.0.9.dist-info/RECORD
