Metadata-Version: 2.4
Name: enumerific
Version: 1.0.9
Summary: Simplifies working with Python enums.
Author: Daniel Sissman
License-Expression: MIT
Project-URL: documentation, https://github.com/bluebinary/enumerific/blob/main/README.md
Project-URL: changelog, https://github.com/bluebinary/enumerific/blob/main/CHANGELOG.md
Project-URL: repository, https://github.com/bluebinary/enumerific
Project-URL: issues, https://github.com/bluebinary/enumerific/issues
Project-URL: homepage, https://github.com/bluebinary/enumerific
Keywords: enum,enumeration,enumerations
Classifier: Programming Language :: Python :: 3
Classifier: Programming Language :: Python :: 3.10
Classifier: Programming Language :: Python :: 3.11
Classifier: Programming Language :: Python :: 3.12
Classifier: Programming Language :: Python :: 3.13
Requires-Python: >=3.10
License-File: LICENSE.md
Provides-Extra: development
Requires-Dist: black==24.10.*; extra == "development"
Requires-Dist: pytest==8.3.*; extra == "development"
Requires-Dist: pytest-codeblocks==0.17.0; extra == "development"
Provides-Extra: distribution
Requires-Dist: build; extra == "distribution"
Requires-Dist: twine; extra == "distribution"
Requires-Dist: wheel; extra == "distribution"
Dynamic: license-file
